vhdl-stuff/fullAdder/design.vhd
-- Code your design here

library IEEE;
use IEEE.std_logic_1164.all;

entity full_adder is
	port (
		a, b, cin : in  std_logic;
		s, cout   : out std_logic
	);
end;

architecture mydesign of full_adder is
begin
	s    <= a xor b xor cin;
	cout <= (a and b) or (cin and b);
end mydesign;

vhdl-stuff/fullAdder/testbench.vhd
--file: testbench.vhd

library IEEE;
use IEEE.std_logic_1164.all;

entity testbench is
end entity;

architecture dataflow of testbench is

	component full_adder is
		port (
			a, b, cin : in  std_logic;
			s, cout   : out std_logic
		);
	end component;

	signal a, b, cin, s, cout : std_logic;
begin
	uut : full_adder port map(
		a    => a,
		b    => b,
		cin  => cin,
		s    => s,
		cout => cout
	);

	a   <= '0', '1' after 80 ns;
	b   <= '0', '1' after 40 ns, '0' after 80 ns, '1' after 120 ns;
	cin <= '1', '0' after 20 ns, '0' after 40 ns, '1' after 60 ns, '0' after 80 ns, '1' after 100 ns,
		'0' after 120 ns, '1' after 140 ns;

end dataflow;

vhdl-stuff/waves/testbench.vcd
$date
  Wed Jul 13 22:15:50 2022
$end
$version
  GHDL v0
$end
$timescale
  1 fs
$end
$scope module standard $end
$upscope $end
$scope module textio $end
$upscope $end
$scope module std_logic_1164 $end
$upscope $end
$scope module testbench $end
$var reg 1 ! a $end
$var reg 1 " b $end
$var reg 1 # cin $end
$var reg 1 $ s $end
$var reg 1 % cout $end
$scope module uut $end
$var reg 1 & a $end
$var reg 1 ' b $end
$var reg 1 ( cin $end
$var reg 1 ) s $end
$var reg 1 * cout $end
$upscope $end
$upscope $end
$enddefinitions $end
#0
0!
0"
1#
1$
0%
0&
0'
1(
1)
0*
#20000000
0#
0$
0(
0)
#40000000
1"
1$
1'
1)
#60000000
1#
0$
1%
1(
0)
1*
#80000000
1!
0"
0#
1$
0%
1&
0'
0(
1)
0*
#100000000
1#
0$
1(
0)
#120000000
1"
0#
1%
1'
0(
1*
#140000000
1#
1$
1(
1)
